probabilistic_quantum_reasoner/__init__.py
probabilistic_quantum_reasoner/licensing.py
probabilistic_quantum_reasoner/backends/__init__.py
probabilistic_quantum_reasoner/backends/pennylane_backend.py
probabilistic_quantum_reasoner/backends/qiskit_backend.py
probabilistic_quantum_reasoner/backends/simulator.py
probabilistic_quantum_reasoner/core/__init__.py
probabilistic_quantum_reasoner/core/exceptions.py
probabilistic_quantum_reasoner/core/network.py
probabilistic_quantum_reasoner/core/nodes.py
probabilistic_quantum_reasoner/core/operators.py
probabilistic_quantum_reasoner/examples/__init__.py
probabilistic_quantum_reasoner/examples/prisoners_dilemma.py
probabilistic_quantum_reasoner/examples/quantum_xor.py
probabilistic_quantum_reasoner/examples/weather_mood.py
probabilistic_quantum_reasoner/inference/__init__.py
probabilistic_quantum_reasoner/inference/belief_propagation.py
probabilistic_quantum_reasoner/inference/causal.py
probabilistic_quantum_reasoner/inference/engine.py
probabilistic_quantum_reasoner/inference/variational.py
probabilistic_quantum_reasoner-1.0.0.dist-info/licenses/LICENSE
probabilistic_quantum_reasoner-1.0.0.dist-info/licenses/license_info.py
probabilistic_quantum_reasoner-1.0.0.dist-info/METADATA
probabilistic_quantum_reasoner-1.0.0.dist-info/WHEEL
probabilistic_quantum_reasoner-1.0.0.dist-info/top_level.txt
probabilistic_quantum_reasoner-1.0.0.dist-info/RECORD
